README.rst
setup.cfg
setup.py
namesync/__init__.py
namesync/config.py
namesync/exceptions.py
namesync/main.py
namesync/records.py
namesync.egg-info/PKG-INFO
namesync.egg-info/SOURCES.txt
namesync.egg-info/dependency_links.txt
namesync.egg-info/entry_points.txt
namesync.egg-info/pbr.json
namesync.egg-info/requires.txt
namesync.egg-info/top_level.txt
namesync/backends/__init__.py
namesync/backends/base.py
namesync/backends/cloudflare.py
namesync/packages/__init__.py
namesync/packages/six.py