Metadata-Version: 1.1
Name: namesync
Version: 0.4
Summary: Sync DNS records stored in a flat file format to your DNS provider.
Home-page: https://github.com/dnerdy/namesync
Author: Mark Sandstrom
Author-email: mark@deliciouslynerdy.com
License: UNKNOWN
Download-URL: https://github.com/dnerdy/namesync/archive/v0.4.tar.gz
Keywords: dns,sync,syncing,cloudflare
Platform: UNKNOWN
Classifier: Development Status :: 4 - Beta
Classifier: Intended Audience :: Developers
Classifier: Intended Audience :: System Administrators
Classifier: License :: OSI Approved :: MIT License
Classifier: Operating System :: OS Independent
Classifier: Programming Language :: Python :: 2.7
Classifier: Programming Language :: Python :: 3.4
Classifier: Topic :: Internet :: Name Service (DNS)
